<?xml version="1.0" encoding="UTF-8"?>
<nicovideo_thumb_response status="ok">
  <thumb>
    <video_id>sm29761151</video_id>
    <title>Tda式改変ミクさんで”おねがいダーリン”</title>
    <description>今回もお着替えしてみました。まだ肩まわりのウエイトが甘いですが・・・</description>
    <thumbnail_url>http://tn-skr4.smilevideo.jp/smile?i=29761151</thumbnail_url>
    <first_retrieve>2016-10-02T20:59:17+09:00</first_retrieve>
    <length>3:16</length>
    <movie_type>mp4</movie_type>
    <size_high>103315922</size_high>
    <size_low>10734766</size_low>
    <view_counter>2678</view_counter>
    <comment_num>38</comment_num>
    <mylist_counter>128</mylist_counter>
    <last_res_body>かわいいいい カメラ切り替えすぎ かわえええ!!! 新作きた! 好み～ GJ 白か 髪綺麗 うぽつです。 このミク好き! 可愛いよおぉ!! 画質がやばい 表情がいい 表情がえろいのぉ お～新作来た かわいいーー カメラワーク俺得 ちょっと待って!めっ. </last_res_body>
    <watch_url>http://www.nicovideo.jp/watch/sm29761151</watch_url>
    <thumb_type>video</thumb_type>
    <embeddable>1</embeddable>
    <no_live_play>0</no_live_play>
    <tags domain="jp">
      <tag category="1" lock="1">VOCALOID</tag>
      <tag lock="1">おねがいダーリン</tag>
      <tag lock="1">Tda式改変モデル</tag>
      <tag lock="1">Tda式改変ミク</tag>
      <tag lock="1">Tda式append</tag>
      <tag lock="1">初音ミク</tag>
      <tag>Tda式Appendミク</tag>
      <tag>MMDパンツリンク</tag>
      <tag>MikuMikuDance</tag>
    </tags>
    <user_id>8899799</user_id>
    <user_nickname>コウ</user_nickname>
    <user_icon_url>http://usericon.nimg.jp/usericon/s/889/8899799.jpg?1457761539</user_icon_url>
  </thumb>
</nicovideo_thumb_response>