<?xml version="1.0" encoding="UTF-8"?>
<nicovideo_thumb_response status="ok">
  <thumb>
    <video_id>sm29752697</video_id>
    <title>【MAYU】タロット依存症 (占いバカ)【オリジナル】</title>
    <description>MAYUはタロットに中毒！(元タイトル：「タロットBAKA」)ボーカル： MAYU作曲・作詞: うさぎラビットILLUS by まつり http://piapro.jp/hnb___m歌詞: http://piapro.jp/t/jnZGオリジナルボカロ曲マイリスト:&amp;nbsp;&amp;nbsp;http://www.nicovideo.jp/mylist/38574099Vocalotracksにてオリジナル曲配信中です。GUMI：「Lost (Nyan)」、「ずっときっと」、「My Magic（もっと萌えマジック）」Lily: 「DRINK-DRINKING-DRUNK」、「STOP! ザ・デブ活！」CUL: 「Bargain Sweeper」、「無敵少女」、「ぼっち宇宙旅」</description>
    <thumbnail_url>http://tn-skr2.smilevideo.jp/smile?i=29752697</thumbnail_url>
    <first_retrieve>2016-10-01T19:45:00+09:00</first_retrieve>
    <length>3:14</length>
    <movie_type>mp4</movie_type>
    <size_high>97843016</size_high>
    <size_low>10337923</size_low>
    <view_counter>213</view_counter>
    <comment_num>6</comment_num>
    <mylist_counter>13</mylist_counter>
    <last_res_body>うぽつです～!! 88888888888888888888 88888888888888888888 888888888 ゜・✽:.。.+(๑??????ᆺ うぽつです! </last_res_body>
    <watch_url>http://www.nicovideo.jp/watch/sm29752697</watch_url>
    <thumb_type>video</thumb_type>
    <embeddable>1</embeddable>
    <no_live_play>0</no_live_play>
    <tags domain="jp">
      <tag category="1" lock="1">VOCALOID</tag>
      <tag lock="1">MAYU</tag>
      <tag lock="1">Vocaloid新曲リンク</tag>
      <tag lock="1">うさぎラビット</tag>
      <tag lock="1">タロット</tag>
      <tag>かわいいぼかうた</tag>
      <tag>占い</tag>
      <tag>レトロ</tag>
      <tag>MAYUオリジナル曲</tag>
      <tag>MAYU(VOCALOID)</tag>
      <tag>まつり</tag>
    </tags>
    <user_id>32665382</user_id>
    <user_nickname>うさぎラビット</user_nickname>
    <user_icon_url>http://usericon.nimg.jp/usericon/s/3266/32665382.jpg?1365842924</user_icon_url>
  </thumb>
</nicovideo_thumb_response>