<?xml version="1.0" encoding="UTF-8"?>
<nicovideo_thumb_response status="ok">
  <thumb>
    <video_id>sm29742940</video_id>
    <title>残像ディストピア/feat.巡音ルカ</title>
    <description>「君のついた優しい嘘が、僕が此処に存在する理由。」作詞/作曲/Movie...書店mylist/57143698 twitter→ @shotenteki_oreIllust............SuGiさん　twitter→ @sugi_214こんにちは、4作目です。「君の名は。」見に行きたいです。前作→ -Refrain- sm290417482016年春M3【K-06a】（サークル名B.E.R）にて、この曲を含めたAlbum『DiMNESS』を500円で頒布予定です。よろしければお立ち寄りください！！</description>
    <thumbnail_url>http://tn-skr1.smilevideo.jp/smile?i=29742940</thumbnail_url>
    <first_retrieve>2016-09-30T19:00:00+09:00</first_retrieve>
    <length>4:05</length>
    <movie_type>mp4</movie_type>
    <size_high>104557715</size_high>
    <size_low>13114506</size_low>
    <view_counter>1811</view_counter>
    <comment_num>31</comment_num>
    <mylist_counter>65</mylist_counter>
    <last_res_body>うぽつです。 ぴあの～ かっちょいいギター 新作待ってました! GJ 雪? すごいなこれ おおお… いいね 綺麗なイラスト うぽつです おおおおおおお 良い!!!! かっこよすぎてやばい いいなああーーー おおおゾクゾクする いいぞおおお かっこいい… お </last_res_body>
    <watch_url>http://www.nicovideo.jp/watch/sm29742940</watch_url>
    <thumb_type>video</thumb_type>
    <embeddable>1</embeddable>
    <no_live_play>0</no_live_play>
    <tags domain="jp">
      <tag category="1" lock="1">VOCALOID</tag>
      <tag lock="1">VOCALEAMO</tag>
      <tag lock="1">巡音ルカ</tag>
      <tag lock="1">VOCAROCK</tag>
      <tag lock="1">巡音ルカV4X</tag>
      <tag lock="1">M3-2016秋</tag>
      <tag>VOCALOID新曲リンク</tag>
      <tag>ルカオリジナル曲</tag>
      <tag>切ないルカうた</tag>
      <tag>メグリーモ</tag>
    </tags>
    <user_id>10545741</user_id>
    <user_nickname>書店@B.E.R</user_nickname>
    <user_icon_url>http://usericon.nimg.jp/usericon/s/1054/10545741.jpg?1460949194</user_icon_url>
  </thumb>
</nicovideo_thumb_response>