<?xml version="1.0" encoding="UTF-8"?>
<nicovideo_thumb_response status="ok">
  <thumb>
    <video_id>sm29747497</video_id>
    <title>【さとうささらオリジナル曲】幻の街</title>
    <description>2年ぶりのささらオリジナル曲。遠方でよく足を運ぶ場所、そこに着くまでに何度も通り過ぎたけど一度行ってみたい場所。そこから、この作品を思いつきました。自作のMMD静画で今回も作っていますが、設定はささらは遠く離れた学校にバスで通学している学生というものになってます。その他作品リストはmylist/4364050です。たてごと♪/カラダに優しいP様、広告ありがとうございました。</description>
    <thumbnail_url>http://tn-skr2.smilevideo.jp/smile?i=29747497</thumbnail_url>
    <first_retrieve>2016-09-30T23:00:00+09:00</first_retrieve>
    <length>4:44</length>
    <movie_type>mp4</movie_type>
    <size_high>92307114</size_high>
    <size_low>13958380</size_low>
    <view_counter>189</view_counter>
    <comment_num>18</comment_num>
    <mylist_counter>16</mylist_counter>
    <last_res_body>GJ(霧 88888888888888888888 夢永しゃんのオトだあ うぽつでーっすヽ(・∀ 888888888888 !? これはきっとファービ </last_res_body>
    <watch_url>http://www.nicovideo.jp/watch/sm29747497</watch_url>
    <thumb_type>video</thumb_type>
    <embeddable>1</embeddable>
    <no_live_play>0</no_live_play>
    <tags domain="jp">
      <tag category="1" lock="1">VOCALOID</tag>
      <tag lock="1">CeVIO</tag>
      <tag lock="1">さとうささら</tag>
      <tag lock="1">ささらオリジナル曲</tag>
      <tag lock="1">夜色P</tag>
      <tag lock="1">ささら.com_掲載OK</tag>
      <tag>CeVIOオリジナル曲</tag>
      <tag>CeVIO新曲リンク</tag>
    </tags>
    <user_id>498070</user_id>
    <user_nickname>夢永美朱(夜色P)</user_nickname>
    <user_icon_url>http://usericon.nimg.jp/usericon/s/49/498070.jpg?1424966032</user_icon_url>
  </thumb>
</nicovideo_thumb_response>