<?xml version="1.0" encoding="UTF-8"?>
<nicovideo_thumb_response status="ok">
  <thumb>
    <video_id>sm29704513</video_id>
    <title>【壊れるほどに…】抱きしめて☆tonight【GUMIオリジナル曲】</title>
    <description>☆が付いてるからセーフ！GUMIによるノスタルジックなポップソングです。おっさんによる乙女な歌詞にもご注目！！素敵なイラストはMASONさんに描いていただきました！本当にありがとうございました！ あ、9/24に三児の父となりました。あ、どうも、ありがとうございます。音楽・動画　No:Re:イラスト　MASONさんTwitter　https://twitter.com/mason_0617SPECIAL THANKS 　D＆K　projectさん　HP http://dk-project.com/index.html前作　sm29597816マイリストmylist/25467438コミュニティ　co2178850 Twitter　NoRe39ブログhttp://ameblo.jp/no-re/ ピアプロhttp://piapro.jp/no0re</description>
    <thumbnail_url>http://tn-skr2.smilevideo.jp/smile?i=29704513</thumbnail_url>
    <first_retrieve>2016-09-30T19:00:00+09:00</first_retrieve>
    <length>4:16</length>
    <movie_type>mp4</movie_type>
    <size_high>19416938</size_high>
    <size_low>13460802</size_low>
    <view_counter>236</view_counter>
    <comment_num>2</comment_num>
    <mylist_counter>5</mylist_counter>
    <last_res_body>よろしくお願いします うぽつーーーーーー!! </last_res_body>
    <watch_url>http://www.nicovideo.jp/watch/sm29704513</watch_url>
    <thumb_type>video</thumb_type>
    <embeddable>1</embeddable>
    <no_live_play>0</no_live_play>
    <tags domain="jp">
      <tag category="1" lock="1">VOCALOID</tag>
      <tag lock="1">GUMI</tag>
      <tag lock="1">GUMIV3</tag>
      <tag lock="1">GUMIオリジナル曲</tag>
      <tag lock="1">No:Re:</tag>
    </tags>
    <user_id>17398747</user_id>
    <user_nickname>No:Re:</user_nickname>
    <user_icon_url>http://usericon.nimg.jp/usericon/s/1739/17398747.jpg?1377088086</user_icon_url>
  </thumb>
</nicovideo_thumb_response>