<?xml version="1.0" encoding="UTF-8"?>
<nicovideo_thumb_response status="ok">
  <thumb>
    <video_id>sm29752354</video_id>
    <title>【ＵＴＡＵオリジナル曲】　夢でダイビング　【健音テイ】</title>
    <description>１０月１日は健音テイの日   ご視聴ありがとうございます！　 ＵＴＡＵオリジナルミュージックビデオ７作目投稿させていただきます。健音テイで「夢でダイビング」です。動画＆ツイッターにコメントいただけるとうれしいです　もれなくしにます坂乃新オリジナル曲　mylist/56174138　　　　　　　ツイッター　　@sakanoshin イラスト、動画　篝乃葛葉さま@SchneeL928 ベース　　ｓｓw114jp様　　＠sswjp2前『星食べる君』←sm29670677　次→近日公開</description>
    <thumbnail_url>http://tn-skr3.smilevideo.jp/smile?i=29752354</thumbnail_url>
    <first_retrieve>2016-10-01T18:01:46+09:00</first_retrieve>
    <length>4:20</length>
    <movie_type>mp4</movie_type>
    <size_high>18576577</size_high>
    <size_low>14131426</size_low>
    <view_counter>221</view_counter>
    <comment_num>10</comment_num>
    <mylist_counter>21</mylist_counter>
    <last_res_body>upotu うぽつです いいね! うぽつ～ ベースかっこいい うぽつです GJGJ うぽつ 相変わらずメロディが GJ8888888888 </last_res_body>
    <watch_url>http://www.nicovideo.jp/watch/sm29752354</watch_url>
    <thumb_type>video</thumb_type>
    <embeddable>1</embeddable>
    <no_live_play>0</no_live_play>
    <tags domain="jp">
      <tag lock="1">ＵＴＡＵオリジナル曲</tag>
      <tag lock="1">ＵＴＡＵ</tag>
      <tag lock="1">健音テイ</tag>
      <tag>VOCALOID</tag>
      <tag>もっと評価されるべき</tag>
      <tag>テイオリジナル曲</tag>
    </tags>
    <user_id>31234851</user_id>
    <user_nickname>坂乃新</user_nickname>
    <user_icon_url>http://usericon.nimg.jp/usericon/s/3123/31234851.jpg?1473612400</user_icon_url>
  </thumb>
</nicovideo_thumb_response>