<?xml version="1.0" encoding="UTF-8"?>
<nicovideo_thumb_response status="ok">
  <thumb>
    <video_id>sm29715612</video_id>
    <title>【初音ミク】　Life Of Your Own　【オリジナル曲】</title>
    <description>EasyPopです。楽曲聴いて頂きありがとうございます。右倣えなんて ごめん被る10/4(火)配信開始のアルバム「Web Dance」収録曲　sm29684826Illust:kiki(mylist/22132873)(@kiki_loid)Music&amp;Lyrics：BETTI(mylist/12749479)(@BETTI0819)off vocaloid：http://piapro.jp/t/LbnqYouTube：https://www.youtube.com/watch?v=37PZbSAOt0k</description>
    <thumbnail_url>http://tn-skr1.smilevideo.jp/smile?i=29715612</thumbnail_url>
    <first_retrieve>2016-09-27T21:00:00+09:00</first_retrieve>
    <length>3:48</length>
    <movie_type>mp4</movie_type>
    <size_high>14051394</size_high>
    <size_low>10334507</size_low>
    <view_counter>3319</view_counter>
    <comment_num>55</comment_num>
    <mylist_counter>160</mylist_counter>
    <last_res_body>8888888888888 うぽつ うぽつ ←俺がいるww 8888888 うぽつ! GJ! うぽつう ミクさん珍しいですね GJ うぽつ やった! うぽつ! 8888888888888 GJ! 歌詞好きだー EasyPopさんの曲好き いい曲でした </last_res_body>
    <watch_url>http://www.nicovideo.jp/watch/sm29715612</watch_url>
    <thumb_type>video</thumb_type>
    <embeddable>1</embeddable>
    <no_live_play>0</no_live_play>
    <tags domain="jp">
      <tag category="1" lock="1">VOCALOID</tag>
      <tag lock="1">EasyPop</tag>
      <tag lock="1">キキ(絵師)</tag>
      <tag lock="1">Life_Of_Your_Own</tag>
      <tag lock="1">初音ミク</tag>
      <tag>VOCALOID新曲リンク</tag>
      <tag>ミクオリジナル曲</tag>
      <tag>お洒落なミクうた</tag>
    </tags>
    <user_id>2423537</user_id>
    <user_nickname>EasyPop/BETTI</user_nickname>
    <user_icon_url>http://usericon.nimg.jp/usericon/s/242/2423537.jpg?1465131091</user_icon_url>
  </thumb>
</nicovideo_thumb_response>