<?xml version="1.0" encoding="UTF-8"?>
<nicovideo_thumb_response status="ok">
  <thumb>
    <video_id>sm29755486</video_id>
    <title>【カラプロ】Must Buy【申請中】</title>
    <description>Must Buy(sm26885680)カラプロ申請カラオケです(+o+)詞 Ukichi 曲 Cabochi 絵 mikuota 写真 nobiko</description>
    <thumbnail_url>http://tn-skr3.smilevideo.jp/smile?i=29755486</thumbnail_url>
    <first_retrieve>2016-10-02T01:03:25+09:00</first_retrieve>
    <length>4:23</length>
    <movie_type>mp4</movie_type>
    <size_high>75649751</size_high>
    <size_low>11660879</size_low>
    <view_counter>13</view_counter>
    <comment_num>0</comment_num>
    <mylist_counter>0</mylist_counter>
    <last_res_body />
    <watch_url>http://www.nicovideo.jp/watch/sm29755486</watch_url>
    <thumb_type>video</thumb_type>
    <embeddable>1</embeddable>
    <no_live_play>0</no_live_play>
    <tags domain="jp">
      <tag category="1" lock="1">VOCALOID</tag>
      <tag lock="1">カラプロ</tag>
    </tags>
    <user_id>50854365</user_id>
    <user_nickname>Uchick</user_nickname>
    <user_icon_url>http://usericon.nimg.jp/usericon/s/5085/50854365.jpg?1470391653</user_icon_url>
  </thumb>
</nicovideo_thumb_response>