<?xml version="1.0" encoding="UTF-8"?>
<nicovideo_thumb_response status="ok">
  <thumb>
    <video_id>sm29766974</video_id>
    <title>【UTAU新音源配布】文学者の恋文【杏美えいは】</title>
    <description>杏美えいはの音源配布動画です。あんえいと呼んであげてください。作詞・作曲：dorikoさん　原曲→sm24186428　原音設定・調声：まいこさん　マイリス→mylist/29356584　twitter→@maiko3tattun　イラスト：たっかーさん　マイリス→mylist/56490575　piapro→http://piapro.jp/Qoo1127　中の人・動画：蓮八　マイリス→mylist/56372534　twitter→@kagaminehamati　音源配布所→http://lenhati.weebly.com/2636025998.html</description>
    <thumbnail_url>http://tn-skr3.smilevideo.jp/smile?i=29766974</thumbnail_url>
    <first_retrieve>2016-10-03T20:33:10+09:00</first_retrieve>
    <length>5:22</length>
    <movie_type>mp4</movie_type>
    <size_high>66620230</size_high>
    <size_low>16459350</size_low>
    <view_counter>39</view_counter>
    <comment_num>1</comment_num>
    <mylist_counter>2</mylist_counter>
    <last_res_body>いいねb </last_res_body>
    <watch_url>http://www.nicovideo.jp/watch/sm29766974</watch_url>
    <thumb_type>video</thumb_type>
    <embeddable>1</embeddable>
    <no_live_play>0</no_live_play>
    <tags domain="jp">
      <tag category="1" lock="1">VOCALOID</tag>
      <tag lock="1">UTAU</tag>
      <tag lock="1">VOCALOID→UTAUカバー曲</tag>
      <tag lock="1">杏美えいは</tag>
      <tag lock="1">あんえい</tag>
      <tag lock="1">UTAU音源配布所リンク</tag>
    </tags>
    <user_id>56723599</user_id>
    <user_nickname>蓮八</user_nickname>
    <user_icon_url>http://usericon.nimg.jp/usericon/s/5672/56723599.jpg?1468396877</user_icon_url>
  </thumb>
</nicovideo_thumb_response>