<?xml version="1.0" encoding="UTF-8"?>
<nicovideo_thumb_response status="ok">
  <thumb>
    <video_id>sm29738148</video_id>
    <title>【オリジナル】時給300億ほしい【GUMI】</title>
    <description>わかる作詞作曲絵:俺調声:26k（mylist/30910932）</description>
    <thumbnail_url>http://tn-skr1.smilevideo.jp/smile?i=29738148</thumbnail_url>
    <first_retrieve>2016-09-29T08:37:05+09:00</first_retrieve>
    <length>4:20</length>
    <movie_type>mp4</movie_type>
    <size_high>19864634</size_high>
    <size_low>11358555</size_low>
    <view_counter>1740</view_counter>
    <comment_num>114</comment_num>
    <mylist_counter>94</mylist_counter>
    <last_res_body>はい? お帰り 何が起こった ? 暴論www 目ぇ死んでるやん お金ほしい 死にたくない 30で童貞卒業させて わかる いいセンスだ。 私も欲しい。共感ww おいしそう わかる アルトパート アルトパートで笑うww おいww わかる 謎の転調 ファー... </last_res_body>
    <watch_url>http://www.nicovideo.jp/watch/sm29738148</watch_url>
    <thumb_type>video</thumb_type>
    <embeddable>1</embeddable>
    <no_live_play>0</no_live_play>
    <tags domain="jp">
      <tag category="1" lock="1">VOCALOID</tag>
      <tag lock="1">GUMIオリジナル曲</tag>
      <tag lock="1">VOCALOIDオリジナル曲</tag>
      <tag>メスシリンダー</tag>
      <tag>26K</tag>
      <tag>時給300億ほしい</tag>
      <tag>あたまわるいうた</tag>
      <tag>まぁねぇ。</tag>
    </tags>
    <user_id>35015984</user_id>
    <user_nickname>綾波型一番艦のほっぺ隊四等兵</user_nickname>
    <user_icon_url>http://usericon.nimg.jp/usericon/s/3501/35015984.jpg?1444369740</user_icon_url>
  </thumb>
</nicovideo_thumb_response>